hashcounter/__init__.py
hashcounter-2025.8.241600.dist-info/licenses/LICENSE
hashcounter-2025.8.241600.dist-info/METADATA
hashcounter-2025.8.241600.dist-info/WHEEL
hashcounter-2025.8.241600.dist-info/top_level.txt
hashcounter-2025.8.241600.dist-info/RECORD
